{"result":[{"imdb_id":"tt8251242","tmdb_id":"213653","title":"The Secret Life of Owls 2018","embed_url":"https:\/\/vidsrc.me\/embed\/tv?imdb=tt8251242","embed_url_tmdb":"https:\/\/vidsrc.me\/embed\/tv?tmdb=213653"},{"imdb_id":"tt14117358","tmdb_id":"117435","title":"Mary McCartney Serves it Up 2021","embed_url":"https:\/\/vidsrc.me\/embed\/tv?imdb=tt14117358","embed_url_tmdb":"https:\/\/vidsrc.me\/embed\/tv?tmdb=117435"},{"imdb_id":"tt21882434","tmdb_id":"211179","title":"Spector 2022","embed_url":"https:\/\/vidsrc.me\/embed\/tv?imdb=tt21882434","embed_url_tmdb":"https:\/\/vidsrc.me\/embed\/tv?tmdb=211179"},{"imdb_id":"tt23033870","tmdb_id":"195627","title":"Mental Coach Jegal 2022","embed_url":"https:\/\/vidsrc.me\/embed\/tv?imdb=tt23033870","embed_url_tmdb":"https:\/\/vidsrc.me\/embed\/tv?tmdb=195627"},{"imdb_id":"tt21103928","tmdb_id":"203592","title":"The Planes That Built Britain with Rob Bell 2022","embed_url":"https:\/\/vidsrc.me\/embed\/tv?imdb=tt21103928","embed_url_tmdb":"https:\/\/vidsrc.me\/embed\/tv?tmdb=203592"},{"imdb_id":"tt18548814","tmdb_id":"238495","title":"Hunted: Into The Wild 1998","embed_url":"https:\/\/vidsrc.me\/embed\/tv?imdb=tt18548814","embed_url_tmdb":"https:\/\/vidsrc.me\/embed\/tv?tmdb=238495"},{"imdb_id":"tt8451992","tmdb_id":"80490","title":"Double Dare (2018) 2018","embed_url":"https:\/\/vidsrc.me\/embed\/tv?imdb=tt8451992","embed_url_tmdb":"https:\/\/vidsrc.me\/embed\/tv?tmdb=80490"},{"imdb_id":"tt3921076","tmdb_id":"65982","title":"Blockbustaz 2016","embed_url":"https:\/\/vidsrc.me\/embed\/tv?imdb=tt3921076","embed_url_tmdb":"https:\/\/vidsrc.me\/embed\/tv?tmdb=65982"},{"imdb_id":"tt5472884","tmdb_id":"101066","title":"Drunk History: Mexico 2016","embed_url":"https:\/\/vidsrc.me\/embed\/tv?imdb=tt5472884","embed_url_tmdb":"https:\/\/vidsrc.me\/embed\/tv?tmdb=101066"},{"imdb_id":"tt23319074","tmdb_id":"213726","title":"The Horne Section TV Show 2022","embed_url":"https:\/\/vidsrc.me\/embed\/tv?imdb=tt23319074","embed_url_tmdb":"https:\/\/vidsrc.me\/embed\/tv?tmdb=213726"},{"imdb_id":"tt1743880","tmdb_id":"39715","title":"Napoleon Dynamite 2012","embed_url":"https:\/\/vidsrc.me\/embed\/tv?imdb=tt1743880","embed_url_tmdb":"https:\/\/vidsrc.me\/embed\/tv?tmdb=39715"},{"imdb_id":"tt21107776","tmdb_id":"212060","title":"Buying Beverly Hills 2022","embed_url":"https:\/\/vidsrc.me\/embed\/tv?imdb=tt21107776","embed_url_tmdb":"https:\/\/vidsrc.me\/embed\/tv?tmdb=212060"},{"imdb_id":"tt21814948","tmdb_id":"211855","title":"The End of Love 2022","embed_url":"https:\/\/vidsrc.me\/embed\/tv?imdb=tt21814948","embed_url_tmdb":"https:\/\/vidsrc.me\/embed\/tv?tmdb=211855"},{"imdb_id":"tt14494944","tmdb_id":"213550","title":"The Final Score 2022","embed_url":"https:\/\/vidsrc.me\/embed\/tv?imdb=tt14494944","embed_url_tmdb":"https:\/\/vidsrc.me\/embed\/tv?tmdb=213550"},{"imdb_id":"tt14518482","tmdb_id":null,"title":"Escape to the Perfect Town ","embed_url":"https:\/\/vidsrc.me\/embed\/tv?imdb=tt14518482"},{"imdb_id":"tt22872838","tmdb_id":"213193","title":"FIFA Uncovered 2022","embed_url":"https:\/\/vidsrc.me\/embed\/tv?imdb=tt22872838","embed_url_tmdb":"https:\/\/vidsrc.me\/embed\/tv?tmdb=213193"},{"imdb_id":"tt22646840","tmdb_id":"213803","title":"The Secret of the Greco Family 2022","embed_url":"https:\/\/vidsrc.me\/embed\/tv?imdb=tt22646840","embed_url_tmdb":"https:\/\/vidsrc.me\/embed\/tv?tmdb=213803"},{"imdb_id":"tt17677144","tmdb_id":"132762","title":"Below Deck Adventure 2022","embed_url":"https:\/\/vidsrc.me\/embed\/tv?imdb=tt17677144","embed_url_tmdb":"https:\/\/vidsrc.me\/embed\/tv?tmdb=132762"},{"imdb_id":"tt20221622","tmdb_id":"214062","title":"The Culpo Sisters 2022","embed_url":"https:\/\/vidsrc.me\/embed\/tv?imdb=tt20221622","embed_url_tmdb":"https:\/\/vidsrc.me\/embed\/tv?tmdb=214062"},{"imdb_id":"tt13622956","tmdb_id":"114463","title":"Zootopia+ 2022","embed_url":"https:\/\/vidsrc.me\/embed\/tv?imdb=tt13622956","embed_url_tmdb":"https:\/\/vidsrc.me\/embed\/tv?tmdb=114463"},{"imdb_id":"tt21924282","tmdb_id":"208738","title":"Jamie's One-Pan Wonders 2022","embed_url":"https:\/\/vidsrc.me\/embed\/tv?imdb=tt21924282","embed_url_tmdb":"https:\/\/vidsrc.me\/embed\/tv?tmdb=208738"},{"imdb_id":"tt0415424","tmdb_id":"2278","title":"Fatherhood 2004","embed_url":"https:\/\/vidsrc.me\/embed\/tv?imdb=tt0415424","embed_url_tmdb":"https:\/\/vidsrc.me\/embed\/tv?tmdb=2278"},{"imdb_id":"tt1705089","tmdb_id":"35128","title":"Strange Sex 2009","embed_url":"https:\/\/vidsrc.me\/embed\/tv?imdb=tt1705089","embed_url_tmdb":"https:\/\/vidsrc.me\/embed\/tv?tmdb=35128"},{"imdb_id":"tt21991254","tmdb_id":"208730","title":"Romantic Killer 2022","embed_url":"https:\/\/vidsrc.me\/embed\/tv?imdb=tt21991254","embed_url_tmdb":"https:\/\/vidsrc.me\/embed\/tv?tmdb=208730"},{"imdb_id":"tt22797034","tmdb_id":"212531","title":"The House Across the Street 2022","embed_url":"https:\/\/vidsrc.me\/embed\/tv?imdb=tt22797034","embed_url_tmdb":"https:\/\/vidsrc.me\/embed\/tv?tmdb=212531"},{"imdb_id":"tt22437106","tmdb_id":"211942","title":"Earthstorm 2022","embed_url":"https:\/\/vidsrc.me\/embed\/tv?imdb=tt22437106","embed_url_tmdb":"https:\/\/vidsrc.me\/embed\/tv?tmdb=211942"},{"imdb_id":"tt20860826","tmdb_id":null,"title":"Wild Latam ","embed_url":"https:\/\/vidsrc.me\/embed\/tv?imdb=tt20860826"},{"imdb_id":"tt21840870","tmdb_id":"211104","title":"Drink Masters 2022","embed_url":"https:\/\/vidsrc.me\/embed\/tv?imdb=tt21840870","embed_url_tmdb":"https:\/\/vidsrc.me\/embed\/tv?tmdb=211104"},{"imdb_id":"tt2279853","tmdb_id":"46410","title":"Guess How Much I Love You 2012","embed_url":"https:\/\/vidsrc.me\/embed\/tv?imdb=tt2279853","embed_url_tmdb":"https:\/\/vidsrc.me\/embed\/tv?tmdb=46410"},{"imdb_id":"tt4057844","tmdb_id":"64029","title":"Open Heart 2015","embed_url":"https:\/\/vidsrc.me\/embed\/tv?imdb=tt4057844","embed_url_tmdb":"https:\/\/vidsrc.me\/embed\/tv?tmdb=64029"},{"imdb_id":"tt22399058","tmdb_id":"197235","title":"Shards of Her 2022","embed_url":"https:\/\/vidsrc.me\/embed\/tv?imdb=tt22399058","embed_url_tmdb":"https:\/\/vidsrc.me\/embed\/tv?tmdb=197235"},{"imdb_id":"tt22437092","tmdb_id":"213288","title":"My Encounter with Evil 2022","embed_url":"https:\/\/vidsrc.me\/embed\/tv?imdb=tt22437092","embed_url_tmdb":"https:\/\/vidsrc.me\/embed\/tv?tmdb=213288"},{"imdb_id":"tt0098813","tmdb_id":"43787","title":"The Green Man 1990","embed_url":"https:\/\/vidsrc.me\/embed\/tv?imdb=tt0098813","embed_url_tmdb":"https:\/\/vidsrc.me\/embed\/tv?tmdb=43787"},{"imdb_id":"tt21221856","tmdb_id":"205461","title":"Freddie Flintoff's Field of Dreams 2022","embed_url":"https:\/\/vidsrc.me\/embed\/tv?imdb=tt21221856","embed_url_tmdb":"https:\/\/vidsrc.me\/embed\/tv?tmdb=205461"},{"imdb_id":"tt15553888","tmdb_id":"213333","title":"I Am a Stalker 2022","embed_url":"https:\/\/vidsrc.me\/embed\/tv?imdb=tt15553888","embed_url_tmdb":"https:\/\/vidsrc.me\/embed\/tv?tmdb=213333"},{"imdb_id":"tt15470672","tmdb_id":"133751","title":"Fred and Rose West: Reopened 2021","embed_url":"https:\/\/vidsrc.me\/embed\/tv?imdb=tt15470672","embed_url_tmdb":"https:\/\/vidsrc.me\/embed\/tv?tmdb=133751"},{"imdb_id":"tt13218362","tmdb_id":"94653","title":"Taskmaster (NO) 2019","embed_url":"https:\/\/vidsrc.me\/embed\/tv?imdb=tt13218362","embed_url_tmdb":"https:\/\/vidsrc.me\/embed\/tv?tmdb=94653"},{"imdb_id":"tt15765450","tmdb_id":"156473","title":"The Calling 2022","embed_url":"https:\/\/vidsrc.me\/embed\/tv?imdb=tt15765450","embed_url_tmdb":"https:\/\/vidsrc.me\/embed\/tv?tmdb=156473"},{"imdb_id":"tt22869540","tmdb_id":"213125","title":"Inside The Sydney Opera House 2022","embed_url":"https:\/\/vidsrc.me\/embed\/tv?imdb=tt22869540","embed_url_tmdb":"https:\/\/vidsrc.me\/embed\/tv?tmdb=213125"},{"imdb_id":"tt0144194","tmdb_id":"12826","title":"Fangface 1978","embed_url":"https:\/\/vidsrc.me\/embed\/tv?imdb=tt0144194","embed_url_tmdb":"https:\/\/vidsrc.me\/embed\/tv?tmdb=12826"},{"imdb_id":"tt2305397","tmdb_id":"45025","title":"Fashion King 2012","embed_url":"https:\/\/vidsrc.me\/embed\/tv?imdb=tt2305397","embed_url_tmdb":"https:\/\/vidsrc.me\/embed\/tv?tmdb=45025"},{"imdb_id":"tt11470588","tmdb_id":"136365","title":"Blackout (2021) 2021","embed_url":"https:\/\/vidsrc.me\/embed\/tv?imdb=tt11470588","embed_url_tmdb":"https:\/\/vidsrc.me\/embed\/tv?tmdb=136365"},{"imdb_id":"tt22751192","tmdb_id":"212218","title":"Pawn Stars Do America 2022","embed_url":"https:\/\/vidsrc.me\/embed\/tv?imdb=tt22751192","embed_url_tmdb":"https:\/\/vidsrc.me\/embed\/tv?tmdb=212218"},{"imdb_id":"tt15040278","tmdb_id":"212512","title":"Mammals 2022","embed_url":"https:\/\/vidsrc.me\/embed\/tv?imdb=tt15040278","embed_url_tmdb":"https:\/\/vidsrc.me\/embed\/tv?tmdb=212512"},{"imdb_id":"tt11771270","tmdb_id":"99346","title":"The English 2022","embed_url":"https:\/\/vidsrc.me\/embed\/tv?imdb=tt11771270","embed_url_tmdb":"https:\/\/vidsrc.me\/embed\/tv?tmdb=99346"},{"imdb_id":"tt2309828","tmdb_id":"3729","title":"High Kick! 2006","embed_url":"https:\/\/vidsrc.me\/embed\/tv?imdb=tt2309828","embed_url_tmdb":"https:\/\/vidsrc.me\/embed\/tv?tmdb=3729"},{"imdb_id":"tt14908664","tmdb_id":"212062","title":"Dirty Rotten Scammers 2022","embed_url":"https:\/\/vidsrc.me\/embed\/tv?imdb=tt14908664","embed_url_tmdb":"https:\/\/vidsrc.me\/embed\/tv?tmdb=212062"},{"imdb_id":"tt21942776","tmdb_id":"213359","title":"Circuit Breakers 2022","embed_url":"https:\/\/vidsrc.me\/embed\/tv?imdb=tt21942776","embed_url_tmdb":"https:\/\/vidsrc.me\/embed\/tv?tmdb=213359"},{"imdb_id":"tt15824600","tmdb_id":"210052","title":"The Big Brunch 2022","embed_url":"https:\/\/vidsrc.me\/embed\/tv?imdb=tt15824600","embed_url_tmdb":"https:\/\/vidsrc.me\/embed\/tv?tmdb=210052"},{"imdb_id":"tt18259002","tmdb_id":null,"title":"n\/A ","embed_url":"https:\/\/vidsrc.me\/embed\/tv?imdb=tt18259002"}],"pages":321}