{"result":[{"imdb_id":"tt8891990","tmdb_id":"83002","title":"Transformers: Cyberverse 2018","embed_url":"https:\/\/vidsrc.me\/embed\/tv?imdb=tt8891990","embed_url_tmdb":"https:\/\/vidsrc.me\/embed\/tv?tmdb=83002"},{"imdb_id":"tt4260668","tmdb_id":null,"title":"n\/A ","embed_url":"https:\/\/vidsrc.me\/embed\/tv?imdb=tt4260668"},{"imdb_id":"tt0112216","tmdb_id":"90690","title":"WMAC Masters 1995","embed_url":"https:\/\/vidsrc.me\/embed\/tv?imdb=tt0112216","embed_url_tmdb":"https:\/\/vidsrc.me\/embed\/tv?tmdb=90690"},{"imdb_id":"tt2220083","tmdb_id":null,"title":"Noel Fielding's Luxury Comedy 2012","embed_url":"https:\/\/vidsrc.me\/embed\/tv?imdb=tt2220083"},{"imdb_id":"tt0101049","tmdb_id":"192","title":"A Bit of Fry & Laurie 1989","embed_url":"https:\/\/vidsrc.me\/embed\/tv?imdb=tt0101049","embed_url_tmdb":"https:\/\/vidsrc.me\/embed\/tv?tmdb=192"},{"imdb_id":"tt12098042","tmdb_id":"115259","title":"Ultimate Supercar 2020","embed_url":"https:\/\/vidsrc.me\/embed\/tv?imdb=tt12098042","embed_url_tmdb":"https:\/\/vidsrc.me\/embed\/tv?tmdb=115259"},{"imdb_id":"tt0995865","tmdb_id":"7084","title":"Lewis Black's Root of All Evil 2008","embed_url":"https:\/\/vidsrc.me\/embed\/tv?imdb=tt0995865","embed_url_tmdb":"https:\/\/vidsrc.me\/embed\/tv?tmdb=7084"},{"imdb_id":"tt0247095","tmdb_id":"11101","title":"Freakylinks 2000","embed_url":"https:\/\/vidsrc.me\/embed\/tv?imdb=tt0247095","embed_url_tmdb":"https:\/\/vidsrc.me\/embed\/tv?tmdb=11101"},{"imdb_id":"tt0144714","tmdb_id":"4377","title":"Highlander: The Raven 1998","embed_url":"https:\/\/vidsrc.me\/embed\/tv?imdb=tt0144714","embed_url_tmdb":"https:\/\/vidsrc.me\/embed\/tv?tmdb=4377"},{"imdb_id":"tt8372660","tmdb_id":"79776","title":"Hunting ISIS 2018","embed_url":"https:\/\/vidsrc.me\/embed\/tv?imdb=tt8372660","embed_url_tmdb":"https:\/\/vidsrc.me\/embed\/tv?tmdb=79776"},{"imdb_id":"tt1294955","tmdb_id":"16358","title":"Total Wipeout 2009","embed_url":"https:\/\/vidsrc.me\/embed\/tv?imdb=tt1294955","embed_url_tmdb":"https:\/\/vidsrc.me\/embed\/tv?tmdb=16358"},{"imdb_id":"tt1678749","tmdb_id":"33002","title":"Mongrels 2010","embed_url":"https:\/\/vidsrc.me\/embed\/tv?imdb=tt1678749","embed_url_tmdb":"https:\/\/vidsrc.me\/embed\/tv?tmdb=33002"},{"imdb_id":"tt0364829","tmdb_id":"1699","title":"Last Comic Standing 2003","embed_url":"https:\/\/vidsrc.me\/embed\/tv?imdb=tt0364829","embed_url_tmdb":"https:\/\/vidsrc.me\/embed\/tv?tmdb=1699"},{"imdb_id":"tt7026882","tmdb_id":"72405","title":"America's War on Drugs 2017","embed_url":"https:\/\/vidsrc.me\/embed\/tv?imdb=tt7026882","embed_url_tmdb":"https:\/\/vidsrc.me\/embed\/tv?tmdb=72405"},{"imdb_id":"tt10379670","tmdb_id":"90278","title":"Alien Highway 2019","embed_url":"https:\/\/vidsrc.me\/embed\/tv?imdb=tt10379670","embed_url_tmdb":"https:\/\/vidsrc.me\/embed\/tv?tmdb=90278"},{"imdb_id":"tt3781670","tmdb_id":"65265","title":"The Pool Master 2014","embed_url":"https:\/\/vidsrc.me\/embed\/tv?imdb=tt3781670","embed_url_tmdb":"https:\/\/vidsrc.me\/embed\/tv?tmdb=65265"},{"imdb_id":"tt1705038","tmdb_id":"33163","title":"G.I. Joe: Renegades 2010","embed_url":"https:\/\/vidsrc.me\/embed\/tv?imdb=tt1705038","embed_url_tmdb":"https:\/\/vidsrc.me\/embed\/tv?tmdb=33163"},{"imdb_id":"tt9140342","tmdb_id":"116174","title":"It's a Sin 2021","embed_url":"https:\/\/vidsrc.me\/embed\/tv?imdb=tt9140342","embed_url_tmdb":"https:\/\/vidsrc.me\/embed\/tv?tmdb=116174"},{"imdb_id":"tt2235759","tmdb_id":"93812","title":"The Great 2020","embed_url":"https:\/\/vidsrc.me\/embed\/tv?imdb=tt2235759","embed_url_tmdb":"https:\/\/vidsrc.me\/embed\/tv?tmdb=93812"},{"imdb_id":"tt1492090","tmdb_id":"18848","title":"Planet Sheen 2010","embed_url":"https:\/\/vidsrc.me\/embed\/tv?imdb=tt1492090","embed_url_tmdb":"https:\/\/vidsrc.me\/embed\/tv?tmdb=18848"},{"imdb_id":"tt3893538","tmdb_id":"60860","title":"Foo Fighters: Sonic Highways 2014","embed_url":"https:\/\/vidsrc.me\/embed\/tv?imdb=tt3893538","embed_url_tmdb":"https:\/\/vidsrc.me\/embed\/tv?tmdb=60860"},{"imdb_id":"tt1406662","tmdb_id":"18660","title":"Miami Medical 2010","embed_url":"https:\/\/vidsrc.me\/embed\/tv?imdb=tt1406662","embed_url_tmdb":"https:\/\/vidsrc.me\/embed\/tv?tmdb=18660"},{"imdb_id":"tt7752034","tmdb_id":"76305","title":"Somebody Feed Phil 2018","embed_url":"https:\/\/vidsrc.me\/embed\/tv?imdb=tt7752034","embed_url_tmdb":"https:\/\/vidsrc.me\/embed\/tv?tmdb=76305"},{"imdb_id":"tt1709198","tmdb_id":"32315","title":"Sym-Bionic Titan 2010","embed_url":"https:\/\/vidsrc.me\/embed\/tv?imdb=tt1709198","embed_url_tmdb":"https:\/\/vidsrc.me\/embed\/tv?tmdb=32315"},{"imdb_id":"tt0094531","tmdb_id":"418","title":"A Pup Named Scooby-Doo 1988","embed_url":"https:\/\/vidsrc.me\/embed\/tv?imdb=tt0094531","embed_url_tmdb":"https:\/\/vidsrc.me\/embed\/tv?tmdb=418"},{"imdb_id":"tt0410985","tmdb_id":"10467","title":"Drew Carey's Green Screen Show 2004","embed_url":"https:\/\/vidsrc.me\/embed\/tv?imdb=tt0410985","embed_url_tmdb":"https:\/\/vidsrc.me\/embed\/tv?tmdb=10467"},{"imdb_id":"tt11534192","tmdb_id":"97141","title":"Justin Bieber: Seasons 2020","embed_url":"https:\/\/vidsrc.me\/embed\/tv?imdb=tt11534192","embed_url_tmdb":"https:\/\/vidsrc.me\/embed\/tv?tmdb=97141"},{"imdb_id":"tt0946601","tmdb_id":"14165","title":"Ruby Gloom 2006","embed_url":"https:\/\/vidsrc.me\/embed\/tv?imdb=tt0946601","embed_url_tmdb":"https:\/\/vidsrc.me\/embed\/tv?tmdb=14165"},{"imdb_id":"tt1553644","tmdb_id":"35305","title":"The Ricky Gervais Show 2010","embed_url":"https:\/\/vidsrc.me\/embed\/tv?imdb=tt1553644","embed_url_tmdb":"https:\/\/vidsrc.me\/embed\/tv?tmdb=35305"},{"imdb_id":"tt0086818","tmdb_id":"38920","title":"The Tripods 1984","embed_url":"https:\/\/vidsrc.me\/embed\/tv?imdb=tt0086818","embed_url_tmdb":"https:\/\/vidsrc.me\/embed\/tv?tmdb=38920"},{"imdb_id":"tt1068683","tmdb_id":"13120","title":"Code Monkeys 2007","embed_url":"https:\/\/vidsrc.me\/embed\/tv?imdb=tt1068683","embed_url_tmdb":"https:\/\/vidsrc.me\/embed\/tv?tmdb=13120"},{"imdb_id":"tt0278877","tmdb_id":"334","title":"Sealab 2021 2000","embed_url":"https:\/\/vidsrc.me\/embed\/tv?imdb=tt0278877","embed_url_tmdb":"https:\/\/vidsrc.me\/embed\/tv?tmdb=334"},{"imdb_id":"tt4908956","tmdb_id":"66056","title":"Atlanta Plastic 2015","embed_url":"https:\/\/vidsrc.me\/embed\/tv?imdb=tt4908956","embed_url_tmdb":"https:\/\/vidsrc.me\/embed\/tv?tmdb=66056"},{"imdb_id":"tt2239947","tmdb_id":"43121","title":"Political Animals 2012","embed_url":"https:\/\/vidsrc.me\/embed\/tv?imdb=tt2239947","embed_url_tmdb":"https:\/\/vidsrc.me\/embed\/tv?tmdb=43121"},{"imdb_id":"tt1711386","tmdb_id":"37016","title":"Dag (2010) 2010","embed_url":"https:\/\/vidsrc.me\/embed\/tv?imdb=tt1711386","embed_url_tmdb":"https:\/\/vidsrc.me\/embed\/tv?tmdb=37016"},{"imdb_id":"tt1538039","tmdb_id":"27003","title":"Cats 101 2008","embed_url":"https:\/\/vidsrc.me\/embed\/tv?imdb=tt1538039","embed_url_tmdb":"https:\/\/vidsrc.me\/embed\/tv?tmdb=27003"},{"imdb_id":"tt1489097","tmdb_id":"32236","title":"WWII in HD 2009","embed_url":"https:\/\/vidsrc.me\/embed\/tv?imdb=tt1489097","embed_url_tmdb":"https:\/\/vidsrc.me\/embed\/tv?tmdb=32236"},{"imdb_id":"tt3108438","tmdb_id":"61552","title":"Catch a Contractor 2014","embed_url":"https:\/\/vidsrc.me\/embed\/tv?imdb=tt3108438","embed_url_tmdb":"https:\/\/vidsrc.me\/embed\/tv?tmdb=61552"},{"imdb_id":"tt10732104","tmdb_id":"97890","title":"Power Book II: Ghost 2020","embed_url":"https:\/\/vidsrc.me\/embed\/tv?imdb=tt10732104","embed_url_tmdb":"https:\/\/vidsrc.me\/embed\/tv?tmdb=97890"},{"imdb_id":"tt8335218","tmdb_id":"110222","title":"No Man's Land (2020) 2020","embed_url":"https:\/\/vidsrc.me\/embed\/tv?imdb=tt8335218","embed_url_tmdb":"https:\/\/vidsrc.me\/embed\/tv?tmdb=110222"},{"imdb_id":"tt1083958","tmdb_id":"13051","title":"The Pick-up Artist 2007","embed_url":"https:\/\/vidsrc.me\/embed\/tv?imdb=tt1083958","embed_url_tmdb":"https:\/\/vidsrc.me\/embed\/tv?tmdb=13051"},{"imdb_id":"tt0075567","tmdb_id":"3488","title":"The Richard Pryor Show 1977","embed_url":"https:\/\/vidsrc.me\/embed\/tv?imdb=tt0075567","embed_url_tmdb":"https:\/\/vidsrc.me\/embed\/tv?tmdb=3488"},{"imdb_id":"tt0103559","tmdb_id":"12544","title":"Street Sharks 1994","embed_url":"https:\/\/vidsrc.me\/embed\/tv?imdb=tt0103559","embed_url_tmdb":"https:\/\/vidsrc.me\/embed\/tv?tmdb=12544"},{"imdb_id":"tt0411024","tmdb_id":"1736","title":"Complete Savages 2004","embed_url":"https:\/\/vidsrc.me\/embed\/tv?imdb=tt0411024","embed_url_tmdb":"https:\/\/vidsrc.me\/embed\/tv?tmdb=1736"},{"imdb_id":"tt9331982","tmdb_id":"95339","title":"The Imagineering Story 2019","embed_url":"https:\/\/vidsrc.me\/embed\/tv?imdb=tt9331982","embed_url_tmdb":"https:\/\/vidsrc.me\/embed\/tv?tmdb=95339"},{"imdb_id":"tt0065307","tmdb_id":"4489","title":"Josie and the Pussycats 1970","embed_url":"https:\/\/vidsrc.me\/embed\/tv?imdb=tt0065307","embed_url_tmdb":"https:\/\/vidsrc.me\/embed\/tv?tmdb=4489"},{"imdb_id":"tt10487072","tmdb_id":"94515","title":"Prank Encounters 2019","embed_url":"https:\/\/vidsrc.me\/embed\/tv?imdb=tt10487072","embed_url_tmdb":"https:\/\/vidsrc.me\/embed\/tv?tmdb=94515"},{"imdb_id":"tt11744632","tmdb_id":"99103","title":"Babies 2020","embed_url":"https:\/\/vidsrc.me\/embed\/tv?imdb=tt11744632","embed_url_tmdb":"https:\/\/vidsrc.me\/embed\/tv?tmdb=99103"},{"imdb_id":"tt0270792","tmdb_id":"7404","title":"The Mole (US) 2001","embed_url":"https:\/\/vidsrc.me\/embed\/tv?imdb=tt0270792","embed_url_tmdb":"https:\/\/vidsrc.me\/embed\/tv?tmdb=7404"},{"imdb_id":"tt11141900","tmdb_id":"97428","title":"Ted Bundy: Falling for a Killer 2020","embed_url":"https:\/\/vidsrc.me\/embed\/tv?imdb=tt11141900","embed_url_tmdb":"https:\/\/vidsrc.me\/embed\/tv?tmdb=97428"}],"pages":321}