{"result":[{"imdb_id":"tt7403736","tmdb_id":"81559","title":"V-Wars 2019","embed_url":"https:\/\/vidsrc.me\/embed\/tv?imdb=tt7403736","embed_url_tmdb":"https:\/\/vidsrc.me\/embed\/tv?tmdb=81559"},{"imdb_id":"tt10394778","tmdb_id":"99412","title":"Vagrant Queen 2020","embed_url":"https:\/\/vidsrc.me\/embed\/tv?imdb=tt10394778","embed_url_tmdb":"https:\/\/vidsrc.me\/embed\/tv?tmdb=99412"},{"imdb_id":"tt4428122","tmdb_id":"62816","title":"Quantico 2015","embed_url":"https:\/\/vidsrc.me\/embed\/tv?imdb=tt4428122","embed_url_tmdb":"https:\/\/vidsrc.me\/embed\/tv?tmdb=62816"},{"imdb_id":"tt5137338","tmdb_id":"67419","title":"Victoria 2016","embed_url":"https:\/\/vidsrc.me\/embed\/tv?imdb=tt5137338","embed_url_tmdb":"https:\/\/vidsrc.me\/embed\/tv?tmdb=67419"},{"imdb_id":"tt3921180","tmdb_id":"62823","title":"Scream: The TV Series 2015","embed_url":"https:\/\/vidsrc.me\/embed\/tv?imdb=tt3921180","embed_url_tmdb":"https:\/\/vidsrc.me\/embed\/tv?tmdb=62823"},{"imdb_id":"tt6021284","tmdb_id":"73554","title":"Liar 2017","embed_url":"https:\/\/vidsrc.me\/embed\/tv?imdb=tt6021284","embed_url_tmdb":"https:\/\/vidsrc.me\/embed\/tv?tmdb=73554"},{"imdb_id":"tt4094300","tmdb_id":"63161","title":"Crazy Ex-Girlfriend 2015","embed_url":"https:\/\/vidsrc.me\/embed\/tv?imdb=tt4094300","embed_url_tmdb":"https:\/\/vidsrc.me\/embed\/tv?tmdb=63161"},{"imdb_id":"tt8594028","tmdb_id":"89314","title":"Reprisal 2019","embed_url":"https:\/\/vidsrc.me\/embed\/tv?imdb=tt8594028","embed_url_tmdb":"https:\/\/vidsrc.me\/embed\/tv?tmdb=89314"},{"imdb_id":"tt2262532","tmdb_id":"46880","title":"The Fosters (2013) 2013","embed_url":"https:\/\/vidsrc.me\/embed\/tv?imdb=tt2262532","embed_url_tmdb":"https:\/\/vidsrc.me\/embed\/tv?tmdb=46880"},{"imdb_id":"tt9169658","tmdb_id":"91962","title":"Emergence 2019","embed_url":"https:\/\/vidsrc.me\/embed\/tv?imdb=tt9169658","embed_url_tmdb":"https:\/\/vidsrc.me\/embed\/tv?tmdb=91962"},{"imdb_id":"tt7661046","tmdb_id":"84584","title":"Dollface 2019","embed_url":"https:\/\/vidsrc.me\/embed\/tv?imdb=tt7661046","embed_url_tmdb":"https:\/\/vidsrc.me\/embed\/tv?tmdb=84584"},{"imdb_id":"tt0983514","tmdb_id":"11294","title":"Kitchen Nightmares (US) 2007","embed_url":"https:\/\/vidsrc.me\/embed\/tv?imdb=tt0983514","embed_url_tmdb":"https:\/\/vidsrc.me\/embed\/tv?tmdb=11294"},{"imdb_id":"tt9077192","tmdb_id":"83247","title":"Haunted (2018) 2018","embed_url":"https:\/\/vidsrc.me\/embed\/tv?imdb=tt9077192","embed_url_tmdb":"https:\/\/vidsrc.me\/embed\/tv?tmdb=83247"},{"imdb_id":"tt0096579","tmdb_id":"2685","title":"Family Matters 1989","embed_url":"https:\/\/vidsrc.me\/embed\/tv?imdb=tt0096579","embed_url_tmdb":"https:\/\/vidsrc.me\/embed\/tv?tmdb=2685"},{"imdb_id":"tt5580540","tmdb_id":"69470","title":"Santa Clarita Diet 2017","embed_url":"https:\/\/vidsrc.me\/embed\/tv?imdb=tt5580540","embed_url_tmdb":"https:\/\/vidsrc.me\/embed\/tv?tmdb=69470"},{"imdb_id":"tt5197820","tmdb_id":"65820","title":"Van Helsing 2016","embed_url":"https:\/\/vidsrc.me\/embed\/tv?imdb=tt5197820","embed_url_tmdb":"https:\/\/vidsrc.me\/embed\/tv?tmdb=65820"},{"imdb_id":"tt1728102","tmdb_id":"35339","title":"Alcatraz 2012","embed_url":"https:\/\/vidsrc.me\/embed\/tv?imdb=tt1728102","embed_url_tmdb":"https:\/\/vidsrc.me\/embed\/tv?tmdb=35339"},{"imdb_id":"tt8409626","tmdb_id":"102970","title":"Cold Courage 2020","embed_url":"https:\/\/vidsrc.me\/embed\/tv?imdb=tt8409626","embed_url_tmdb":"https:\/\/vidsrc.me\/embed\/tv?tmdb=102970"},{"imdb_id":"tt0060036","tmdb_id":"103","title":"The Time Tunnel 1966","embed_url":"https:\/\/vidsrc.me\/embed\/tv?imdb=tt0060036","embed_url_tmdb":"https:\/\/vidsrc.me\/embed\/tv?tmdb=103"},{"imdb_id":"tt0462128","tmdb_id":"4402","title":"The New Adventures of Old Christine 2006","embed_url":"https:\/\/vidsrc.me\/embed\/tv?imdb=tt0462128","embed_url_tmdb":"https:\/\/vidsrc.me\/embed\/tv?tmdb=4402"},{"imdb_id":"tt9103932","tmdb_id":"91724","title":"Greatest Events of WWII in Colour 2019","embed_url":"https:\/\/vidsrc.me\/embed\/tv?imdb=tt9103932","embed_url_tmdb":"https:\/\/vidsrc.me\/embed\/tv?tmdb=91724"},{"imdb_id":"tt11600174","tmdb_id":"98735","title":"The Pharmacist 2020","embed_url":"https:\/\/vidsrc.me\/embed\/tv?imdb=tt11600174","embed_url_tmdb":"https:\/\/vidsrc.me\/embed\/tv?tmdb=98735"},{"imdb_id":"tt8521376","tmdb_id":"103783","title":"Little Voice 2020","embed_url":"https:\/\/vidsrc.me\/embed\/tv?imdb=tt8521376","embed_url_tmdb":"https:\/\/vidsrc.me\/embed\/tv?tmdb=103783"},{"imdb_id":"tt1183865","tmdb_id":"39362","title":"Alphas 2011","embed_url":"https:\/\/vidsrc.me\/embed\/tv?imdb=tt1183865","embed_url_tmdb":"https:\/\/vidsrc.me\/embed\/tv?tmdb=39362"},{"imdb_id":"tt4687880","tmdb_id":"67384","title":"Goliath 2016","embed_url":"https:\/\/vidsrc.me\/embed\/tv?imdb=tt4687880","embed_url_tmdb":"https:\/\/vidsrc.me\/embed\/tv?tmdb=67384"},{"imdb_id":"tt8690518","tmdb_id":"100412","title":"The Baby-Sitters Club (2020) 2020","embed_url":"https:\/\/vidsrc.me\/embed\/tv?imdb=tt8690518","embed_url_tmdb":"https:\/\/vidsrc.me\/embed\/tv?tmdb=100412"},{"imdb_id":"tt0053494","tmdb_id":"291","title":"Coronation Street 1960","embed_url":"https:\/\/vidsrc.me\/embed\/tv?imdb=tt0053494","embed_url_tmdb":"https:\/\/vidsrc.me\/embed\/tv?tmdb=291"},{"imdb_id":"tt2788432","tmdb_id":"64513","title":"American Crime Story 2016","embed_url":"https:\/\/vidsrc.me\/embed\/tv?imdb=tt2788432","embed_url_tmdb":"https:\/\/vidsrc.me\/embed\/tv?tmdb=64513"},{"imdb_id":"tt9644058","tmdb_id":"94853","title":"Guilt (2019) 2019","embed_url":"https:\/\/vidsrc.me\/embed\/tv?imdb=tt9644058","embed_url_tmdb":"https:\/\/vidsrc.me\/embed\/tv?tmdb=94853"},{"imdb_id":"tt3501074","tmdb_id":"61378","title":"Madam Secretary 2014","embed_url":"https:\/\/vidsrc.me\/embed\/tv?imdb=tt3501074","embed_url_tmdb":"https:\/\/vidsrc.me\/embed\/tv?tmdb=61378"},{"imdb_id":"tt0105950","tmdb_id":"13943","title":"Beavis and Butt-Head 1993","embed_url":"https:\/\/vidsrc.me\/embed\/tv?imdb=tt0105950","embed_url_tmdb":"https:\/\/vidsrc.me\/embed\/tv?tmdb=13943"},{"imdb_id":"tt1626038","tmdb_id":"33623","title":"The Avengers: Earth's Mightiest Heroes 2010","embed_url":"https:\/\/vidsrc.me\/embed\/tv?imdb=tt1626038","embed_url_tmdb":"https:\/\/vidsrc.me\/embed\/tv?tmdb=33623"},{"imdb_id":"tt2431438","tmdb_id":"61664","title":"Sense8 2015","embed_url":"https:\/\/vidsrc.me\/embed\/tv?imdb=tt2431438","embed_url_tmdb":"https:\/\/vidsrc.me\/embed\/tv?tmdb=61664"},{"imdb_id":"tt0047720","tmdb_id":"947","title":"Cheyenne 1955","embed_url":"https:\/\/vidsrc.me\/embed\/tv?imdb=tt0047720","embed_url_tmdb":"https:\/\/vidsrc.me\/embed\/tv?tmdb=947"},{"imdb_id":"tt7134908","tmdb_id":"76669","title":"Elite 2018","embed_url":"https:\/\/vidsrc.me\/embed\/tv?imdb=tt7134908","embed_url_tmdb":"https:\/\/vidsrc.me\/embed\/tv?tmdb=76669"},{"imdb_id":"tt2249007","tmdb_id":"1423","title":"Ray Donovan 2013","embed_url":"https:\/\/vidsrc.me\/embed\/tv?imdb=tt2249007","embed_url_tmdb":"https:\/\/vidsrc.me\/embed\/tv?tmdb=1423"},{"imdb_id":"tt10380768","tmdb_id":"102316","title":"Love Life 2020","embed_url":"https:\/\/vidsrc.me\/embed\/tv?imdb=tt10380768","embed_url_tmdb":"https:\/\/vidsrc.me\/embed\/tv?tmdb=102316"},{"imdb_id":"tt0041038","tmdb_id":"31179","title":"The Lone Ranger 1949","embed_url":"https:\/\/vidsrc.me\/embed\/tv?imdb=tt0041038","embed_url_tmdb":"https:\/\/vidsrc.me\/embed\/tv?tmdb=31179"},{"imdb_id":"tt3413236","tmdb_id":"61096","title":"Rush (2014) 2014","embed_url":"https:\/\/vidsrc.me\/embed\/tv?imdb=tt3413236","embed_url_tmdb":"https:\/\/vidsrc.me\/embed\/tv?tmdb=61096"},{"imdb_id":"tt3743822","tmdb_id":"62286","title":"Fear the Walking Dead 2015","embed_url":"https:\/\/vidsrc.me\/embed\/tv?imdb=tt3743822","embed_url_tmdb":"https:\/\/vidsrc.me\/embed\/tv?tmdb=62286"},{"imdb_id":"tt2645122","tmdb_id":"46621","title":"Janet King 2014","embed_url":"https:\/\/vidsrc.me\/embed\/tv?imdb=tt2645122","embed_url_tmdb":"https:\/\/vidsrc.me\/embed\/tv?tmdb=46621"},{"imdb_id":"tt0373732","tmdb_id":"2604","title":"The Boondocks 2005","embed_url":"https:\/\/vidsrc.me\/embed\/tv?imdb=tt0373732","embed_url_tmdb":"https:\/\/vidsrc.me\/embed\/tv?tmdb=2604"},{"imdb_id":"tt2492296","tmdb_id":"63248","title":"Show Me a Hero 2015","embed_url":"https:\/\/vidsrc.me\/embed\/tv?imdb=tt2492296","embed_url_tmdb":"https:\/\/vidsrc.me\/embed\/tv?tmdb=63248"},{"imdb_id":"tt7161312","tmdb_id":"83059","title":"Informer 2018","embed_url":"https:\/\/vidsrc.me\/embed\/tv?imdb=tt7161312","embed_url_tmdb":"https:\/\/vidsrc.me\/embed\/tv?tmdb=83059"},{"imdb_id":"tt6734482","tmdb_id":"72061","title":"The Loch 2017","embed_url":"https:\/\/vidsrc.me\/embed\/tv?imdb=tt6734482","embed_url_tmdb":"https:\/\/vidsrc.me\/embed\/tv?tmdb=72061"},{"imdb_id":"tt1043813","tmdb_id":"75450","title":"Titans (2018) 2018","embed_url":"https:\/\/vidsrc.me\/embed\/tv?imdb=tt1043813","embed_url_tmdb":"https:\/\/vidsrc.me\/embed\/tv?tmdb=75450"},{"imdb_id":"tt2362694","tmdb_id":"48000","title":"Your Pretty Face is Going to Hell 2013","embed_url":"https:\/\/vidsrc.me\/embed\/tv?imdb=tt2362694","embed_url_tmdb":"https:\/\/vidsrc.me\/embed\/tv?tmdb=48000"},{"imdb_id":"tt0046600","tmdb_id":"10118","title":"Father Knows Best 1954","embed_url":"https:\/\/vidsrc.me\/embed\/tv?imdb=tt0046600","embed_url_tmdb":"https:\/\/vidsrc.me\/embed\/tv?tmdb=10118"},{"imdb_id":"tt12370124","tmdb_id":"104999","title":"Floor Is Lava 2020","embed_url":"https:\/\/vidsrc.me\/embed\/tv?imdb=tt12370124","embed_url_tmdb":"https:\/\/vidsrc.me\/embed\/tv?tmdb=104999"},{"imdb_id":"tt0121955","tmdb_id":"2190","title":"South Park 1997","embed_url":"https:\/\/vidsrc.me\/embed\/tv?imdb=tt0121955","embed_url_tmdb":"https:\/\/vidsrc.me\/embed\/tv?tmdb=2190"}],"pages":321}