{"result":[{"imdb_id":"tt0096114","tmdb_id":"107420","title":"The Sisterhood 1988","embed_url":"https:\/\/vidsrc.me\/embed\/movie?imdb=tt0096114","embed_url_tmdb":"https:\/\/vidsrc.me\/embed\/movie?tmdb=107420","quality":"720p"},{"imdb_id":"tt0095904","tmdb_id":"48309","title":"Prison 1987","embed_url":"https:\/\/vidsrc.me\/embed\/movie?imdb=tt0095904","embed_url_tmdb":"https:\/\/vidsrc.me\/embed\/movie?tmdb=48309","quality":"1080p"},{"imdb_id":"tt0095878","tmdb_id":"71048","title":"Pledge Night 1988","embed_url":"https:\/\/vidsrc.me\/embed\/movie?imdb=tt0095878","embed_url_tmdb":"https:\/\/vidsrc.me\/embed\/movie?tmdb=71048","quality":"1080p"},{"imdb_id":"tt7579446","tmdb_id":"619947","title":"Tuscaloosa 2019","embed_url":"https:\/\/vidsrc.me\/embed\/movie?imdb=tt7579446","embed_url_tmdb":"https:\/\/vidsrc.me\/embed\/movie?tmdb=619947","quality":"1080p"},{"imdb_id":"tt0095348","tmdb_id":"17006","title":"I'm Gonna Git You Sucka 1988","embed_url":"https:\/\/vidsrc.me\/embed\/movie?imdb=tt0095348","embed_url_tmdb":"https:\/\/vidsrc.me\/embed\/movie?tmdb=17006","quality":"1080p"},{"imdb_id":"tt0058632","tmdb_id":"109168","title":"Code 7, Victim 5 1964","embed_url":"https:\/\/vidsrc.me\/embed\/movie?imdb=tt0058632","embed_url_tmdb":"https:\/\/vidsrc.me\/embed\/movie?tmdb=109168","quality":"1080p"},{"imdb_id":"tt0107206","tmdb_id":"9386","title":"In the Line of Fire 1993","embed_url":"https:\/\/vidsrc.me\/embed\/movie?imdb=tt0107206","embed_url_tmdb":"https:\/\/vidsrc.me\/embed\/movie?tmdb=9386","quality":"1080p"},{"imdb_id":"tt0100814","tmdb_id":"9362","title":"Tremors 1990","embed_url":"https:\/\/vidsrc.me\/embed\/movie?imdb=tt0100814","embed_url_tmdb":"https:\/\/vidsrc.me\/embed\/movie?tmdb=9362","quality":"1080p"},{"imdb_id":"tt0098663","tmdb_id":"183","title":"The Wizard 1989","embed_url":"https:\/\/vidsrc.me\/embed\/movie?imdb=tt0098663","embed_url_tmdb":"https:\/\/vidsrc.me\/embed\/movie?tmdb=183","quality":"1080p"},{"imdb_id":"tt0118708","tmdb_id":"9622","title":"Beverly Hills Ninja 1997","embed_url":"https:\/\/vidsrc.me\/embed\/movie?imdb=tt0118708","embed_url_tmdb":"https:\/\/vidsrc.me\/embed\/movie?tmdb=9622","quality":"1080p"},{"imdb_id":"tt0118301","tmdb_id":"14557","title":"Dead Man on Campus 1998","embed_url":"https:\/\/vidsrc.me\/embed\/movie?imdb=tt0118301","embed_url_tmdb":"https:\/\/vidsrc.me\/embed\/movie?tmdb=14557","quality":"1080p"},{"imdb_id":"tt0116583","tmdb_id":"10545","title":"The Hunchback of Notre Dame 1996","embed_url":"https:\/\/vidsrc.me\/embed\/movie?imdb=tt0116583","embed_url_tmdb":"https:\/\/vidsrc.me\/embed\/movie?tmdb=10545","quality":"1080p"},{"imdb_id":"tt0112281","tmdb_id":"9273","title":"Ace Ventura: When Nature Calls 1995","embed_url":"https:\/\/vidsrc.me\/embed\/movie?imdb=tt0112281","embed_url_tmdb":"https:\/\/vidsrc.me\/embed\/movie?tmdb=9273","quality":"1080p"},{"imdb_id":"tt0105695","tmdb_id":"33","title":"Unforgiven 1992","embed_url":"https:\/\/vidsrc.me\/embed\/movie?imdb=tt0105695","embed_url_tmdb":"https:\/\/vidsrc.me\/embed\/movie?tmdb=33","quality":"1080p"},{"imdb_id":"tt0107977","tmdb_id":"8005","title":"Robin Hood: Men in Tights 1993","embed_url":"https:\/\/vidsrc.me\/embed\/movie?imdb=tt0107977","embed_url_tmdb":"https:\/\/vidsrc.me\/embed\/movie?tmdb=8005","quality":"1080p"},{"imdb_id":"tt0095776","tmdb_id":"12233","title":"Oliver & Company 1988","embed_url":"https:\/\/vidsrc.me\/embed\/movie?imdb=tt0095776","embed_url_tmdb":"https:\/\/vidsrc.me\/embed\/movie?tmdb=12233","quality":"1080p"},{"imdb_id":"tt0106438","tmdb_id":"94794","title":"Blue 1993","embed_url":"https:\/\/vidsrc.me\/embed\/movie?imdb=tt0106438","embed_url_tmdb":"https:\/\/vidsrc.me\/embed\/movie?tmdb=94794","quality":"1080p"},{"imdb_id":"tt0106335","tmdb_id":"5051","title":"The Baby of M\u00e2con 1993","embed_url":"https:\/\/vidsrc.me\/embed\/movie?imdb=tt0106335","embed_url_tmdb":"https:\/\/vidsrc.me\/embed\/movie?tmdb=5051","quality":"1080p"},{"imdb_id":"tt0108162","tmdb_id":"867","title":"Sliver 1993","embed_url":"https:\/\/vidsrc.me\/embed\/movie?imdb=tt0108162","embed_url_tmdb":"https:\/\/vidsrc.me\/embed\/movie?tmdb=867","quality":"1080p"},{"imdb_id":"tt0103112","tmdb_id":"10750","title":"Toy Soldiers 1991","embed_url":"https:\/\/vidsrc.me\/embed\/movie?imdb=tt0103112","embed_url_tmdb":"https:\/\/vidsrc.me\/embed\/movie?tmdb=10750","quality":"1080p"},{"imdb_id":"tt0104418","tmdb_id":"16191","title":"Highway to Hell 1991","embed_url":"https:\/\/vidsrc.me\/embed\/movie?imdb=tt0104418","embed_url_tmdb":"https:\/\/vidsrc.me\/embed\/movie?tmdb=16191","quality":"1080p"},{"imdb_id":"tt0102138","tmdb_id":"820","title":"JFK 1991","embed_url":"https:\/\/vidsrc.me\/embed\/movie?imdb=tt0102138","embed_url_tmdb":"https:\/\/vidsrc.me\/embed\/movie?tmdb=820","quality":"1080p"},{"imdb_id":"tt0097351","tmdb_id":"2323","title":"Field of Dreams 1989","embed_url":"https:\/\/vidsrc.me\/embed\/movie?imdb=tt0097351","embed_url_tmdb":"https:\/\/vidsrc.me\/embed\/movie?tmdb=2323","quality":"1080p"},{"imdb_id":"tt0097044","tmdb_id":"3064","title":"Chances Are 1989","embed_url":"https:\/\/vidsrc.me\/embed\/movie?imdb=tt0097044","embed_url_tmdb":"https:\/\/vidsrc.me\/embed\/movie?tmdb=3064","quality":"1080p"},{"imdb_id":"tt0107843","tmdb_id":"10498","title":"Point of No Return 1993","embed_url":"https:\/\/vidsrc.me\/embed\/movie?imdb=tt0107843","embed_url_tmdb":"https:\/\/vidsrc.me\/embed\/movie?tmdb=10498","quality":"1080p"},{"imdb_id":"tt0118111","tmdb_id":"16448","title":"Waiting for Guffman 1996","embed_url":"https:\/\/vidsrc.me\/embed\/movie?imdb=tt0118111","embed_url_tmdb":"https:\/\/vidsrc.me\/embed\/movie?tmdb=16448","quality":"1080p"},{"imdb_id":"tt0095877","tmdb_id":"48457","title":"Platoon Leader 1988","embed_url":"https:\/\/vidsrc.me\/embed\/movie?imdb=tt0095877","embed_url_tmdb":"https:\/\/vidsrc.me\/embed\/movie?tmdb=48457","quality":"1080p"},{"imdb_id":"tt0099740","tmdb_id":"11309","title":"Hardware 1990","embed_url":"https:\/\/vidsrc.me\/embed\/movie?imdb=tt0099740","embed_url_tmdb":"https:\/\/vidsrc.me\/embed\/movie?tmdb=11309","quality":"1080p"},{"imdb_id":"tt0120245","tmdb_id":"21749","title":"Super Speedway 1997","embed_url":"https:\/\/vidsrc.me\/embed\/movie?imdb=tt0120245","embed_url_tmdb":"https:\/\/vidsrc.me\/embed\/movie?tmdb=21749","quality":"1080p"},{"imdb_id":"tt0120695","tmdb_id":"10213","title":"From Dusk Till Dawn 3: The Hangman's Daughter 1999","embed_url":"https:\/\/vidsrc.me\/embed\/movie?imdb=tt0120695","embed_url_tmdb":"https:\/\/vidsrc.me\/embed\/movie?tmdb=10213","quality":"1080p"},{"imdb_id":"tt0120481","tmdb_id":"45019","title":"Washington Square 1997","embed_url":"https:\/\/vidsrc.me\/embed\/movie?imdb=tt0120481","embed_url_tmdb":"https:\/\/vidsrc.me\/embed\/movie?tmdb=45019","quality":"1080p"},{"imdb_id":"tt0120428","tmdb_id":"34125","title":"Vampire Journals 1997","embed_url":"https:\/\/vidsrc.me\/embed\/movie?imdb=tt0120428","embed_url_tmdb":"https:\/\/vidsrc.me\/embed\/movie?tmdb=34125","quality":"1080p"},{"imdb_id":"tt0120484","tmdb_id":"10663","title":"The Waterboy 1998","embed_url":"https:\/\/vidsrc.me\/embed\/movie?imdb=tt0120484","embed_url_tmdb":"https:\/\/vidsrc.me\/embed\/movie?tmdb=10663","quality":"1080p"},{"imdb_id":"tt0120142","tmdb_id":"36807","title":"The Sixth Man 1997","embed_url":"https:\/\/vidsrc.me\/embed\/movie?imdb=tt0120142","embed_url_tmdb":"https:\/\/vidsrc.me\/embed\/movie?tmdb=36807","quality":"720p"},{"imdb_id":"tt0119210","tmdb_id":"10871","title":"Switchback 1997","embed_url":"https:\/\/vidsrc.me\/embed\/movie?imdb=tt0119210","embed_url_tmdb":"https:\/\/vidsrc.me\/embed\/movie?tmdb=10871","quality":"1080p"},{"imdb_id":"tt0120082","tmdb_id":"4233","title":"Scream 2 1997","embed_url":"https:\/\/vidsrc.me\/embed\/movie?imdb=tt0120082","embed_url_tmdb":"https:\/\/vidsrc.me\/embed\/movie?tmdb=4233","quality":"1080p"},{"imdb_id":"tt0120032","tmdb_id":"9611","title":"Romy and Michele's High School Reunion 1997","embed_url":"https:\/\/vidsrc.me\/embed\/movie?imdb=tt0120032","embed_url_tmdb":"https:\/\/vidsrc.me\/embed\/movie?tmdb=9611","quality":"1080p"},{"imdb_id":"tt0119908","tmdb_id":"18222","title":"Poison Ivy: The New Seduction 1997","embed_url":"https:\/\/vidsrc.me\/embed\/movie?imdb=tt0119908","embed_url_tmdb":"https:\/\/vidsrc.me\/embed\/movie?tmdb=18222","quality":"1080p"},{"imdb_id":"tt0119807","tmdb_id":"11676","title":"Nothing to Lose 1997","embed_url":"https:\/\/vidsrc.me\/embed\/movie?imdb=tt0119807","embed_url_tmdb":"https:\/\/vidsrc.me\/embed\/movie?tmdb=11676","quality":"1080p"},{"imdb_id":"tt0119258","tmdb_id":"5762","title":"Bounty Hunters 2: Hardball 1997","embed_url":"https:\/\/vidsrc.me\/embed\/movie?imdb=tt0119258","embed_url_tmdb":"https:\/\/vidsrc.me\/embed\/movie?tmdb=5762","quality":"720p"},{"imdb_id":"tt0119164","tmdb_id":"9427","title":"The Full Monty 1997","embed_url":"https:\/\/vidsrc.me\/embed\/movie?imdb=tt0119164","embed_url_tmdb":"https:\/\/vidsrc.me\/embed\/movie?tmdb=9427","quality":"1080p"},{"imdb_id":"tt0119062","tmdb_id":"46625","title":"The End of Violence 1997","embed_url":"https:\/\/vidsrc.me\/embed\/movie?imdb=tt0119062","embed_url_tmdb":"https:\/\/vidsrc.me\/embed\/movie?tmdb=46625","quality":"1080p"},{"imdb_id":"tt0119114","tmdb_id":"1610","title":"Fever Pitch 1997","embed_url":"https:\/\/vidsrc.me\/embed\/movie?imdb=tt0119114","embed_url_tmdb":"https:\/\/vidsrc.me\/embed\/movie?tmdb=1610","quality":"1080p"},{"imdb_id":"tt0118966","tmdb_id":"9458","title":"Desperate Measures 1998","embed_url":"https:\/\/vidsrc.me\/embed\/movie?imdb=tt0118966","embed_url_tmdb":"https:\/\/vidsrc.me\/embed\/movie?tmdb=9458","quality":"1080p"},{"imdb_id":"tt0118929","tmdb_id":"2666","title":"Dark City 1998","embed_url":"https:\/\/vidsrc.me\/embed\/movie?imdb=tt0118929","embed_url_tmdb":"https:\/\/vidsrc.me\/embed\/movie?tmdb=2666","quality":"1080p"},{"imdb_id":"tt0080130","tmdb_id":"45964","title":"When a Stranger Calls 1979","embed_url":"https:\/\/vidsrc.me\/embed\/movie?imdb=tt0080130","embed_url_tmdb":"https:\/\/vidsrc.me\/embed\/movie?tmdb=45964","quality":"1080p"},{"imdb_id":"tt0119282","tmdb_id":"11970","title":"Hercules 1997","embed_url":"https:\/\/vidsrc.me\/embed\/movie?imdb=tt0119282","embed_url_tmdb":"https:\/\/vidsrc.me\/embed\/movie?tmdb=11970","quality":"1080p"},{"imdb_id":"tt0118692","tmdb_id":"13313","title":"Beauty and the Beast: The Enchanted Christmas 1997","embed_url":"https:\/\/vidsrc.me\/embed\/movie?imdb=tt0118692","embed_url_tmdb":"https:\/\/vidsrc.me\/embed\/movie?tmdb=13313","quality":"1080p"},{"imdb_id":"tt0120514","tmdb_id":"11365","title":"Wilde 1997","embed_url":"https:\/\/vidsrc.me\/embed\/movie?imdb=tt0120514","embed_url_tmdb":"https:\/\/vidsrc.me\/embed\/movie?tmdb=11365","quality":"1080p"},{"imdb_id":"tt0120148","tmdb_id":"10215","title":"Sliding Doors 1998","embed_url":"https:\/\/vidsrc.me\/embed\/movie?imdb=tt0120148","embed_url_tmdb":"https:\/\/vidsrc.me\/embed\/movie?tmdb=10215","quality":"1080p"}],"pages":1543}