{"result":[{"imdb_id":"tt0043619","tmdb_id":"83670","title":"Hard, Fast and Beautiful 1951","embed_url":"https:\/\/vidsrc.me\/embed\/movie?imdb=tt0043619","embed_url_tmdb":"https:\/\/vidsrc.me\/embed\/movie?tmdb=83670","quality":"DVD"},{"imdb_id":"tt0906665","tmdb_id":"13637","title":"Sukiyaki Western Django 2007","embed_url":"https:\/\/vidsrc.me\/embed\/movie?imdb=tt0906665","embed_url_tmdb":"https:\/\/vidsrc.me\/embed\/movie?tmdb=13637","quality":"1080p"},{"imdb_id":"tt0380687","tmdb_id":"9976","title":"Satan's Little Helper 2004","embed_url":"https:\/\/vidsrc.me\/embed\/movie?imdb=tt0380687","embed_url_tmdb":"https:\/\/vidsrc.me\/embed\/movie?tmdb=9976","quality":"1080p"},{"imdb_id":"tt0057069","tmdb_id":"42990","title":"40 Pounds of Trouble 1962","embed_url":"https:\/\/vidsrc.me\/embed\/movie?imdb=tt0057069","embed_url_tmdb":"https:\/\/vidsrc.me\/embed\/movie?tmdb=42990","quality":"1080p"},{"imdb_id":"tt0111488","tmdb_id":"41590","title":"Trial by Jury 1994","embed_url":"https:\/\/vidsrc.me\/embed\/movie?imdb=tt0111488","embed_url_tmdb":"https:\/\/vidsrc.me\/embed\/movie?tmdb=41590","quality":"1080p"},{"imdb_id":"tt0150662","tmdb_id":"11634","title":"Show Me Love 1998","embed_url":"https:\/\/vidsrc.me\/embed\/movie?imdb=tt0150662","embed_url_tmdb":"https:\/\/vidsrc.me\/embed\/movie?tmdb=11634","quality":"1080p"},{"imdb_id":"tt0125659","tmdb_id":"1902","title":"Open Your Eyes 1997","embed_url":"https:\/\/vidsrc.me\/embed\/movie?imdb=tt0125659","embed_url_tmdb":"https:\/\/vidsrc.me\/embed\/movie?tmdb=1902","quality":"1080p"},{"imdb_id":"tt0104870","tmdb_id":"87321","title":"Mikey 1992","embed_url":"https:\/\/vidsrc.me\/embed\/movie?imdb=tt0104870","embed_url_tmdb":"https:\/\/vidsrc.me\/embed\/movie?tmdb=87321","quality":"1080p"},{"imdb_id":"tt0044423","tmdb_id":"30345","title":"The Black Castle 1952","embed_url":"https:\/\/vidsrc.me\/embed\/movie?imdb=tt0044423","embed_url_tmdb":"https:\/\/vidsrc.me\/embed\/movie?tmdb=30345","quality":"1080p"},{"imdb_id":"tt0036975","tmdb_id":"84710","title":"Jungle Woman 1944","embed_url":"https:\/\/vidsrc.me\/embed\/movie?imdb=tt0036975","embed_url_tmdb":"https:\/\/vidsrc.me\/embed\/movie?tmdb=84710","quality":"1080p"},{"imdb_id":"tt0058930","tmdb_id":"95548","title":"Baby, the Rain Must Fall 1965","embed_url":"https:\/\/vidsrc.me\/embed\/movie?imdb=tt0058930","embed_url_tmdb":"https:\/\/vidsrc.me\/embed\/movie?tmdb=95548","quality":"1080p"},{"imdb_id":"tt0101609","tmdb_id":"37307","title":"Conagher 1991","embed_url":"https:\/\/vidsrc.me\/embed\/movie?imdb=tt0101609","embed_url_tmdb":"https:\/\/vidsrc.me\/embed\/movie?tmdb=37307","quality":"1080p"},{"imdb_id":"tt0020163","tmdb_id":"347","title":"People on Sunday 1930","embed_url":"https:\/\/vidsrc.me\/embed\/movie?imdb=tt0020163","embed_url_tmdb":"https:\/\/vidsrc.me\/embed\/movie?tmdb=347","quality":"1080p"},{"imdb_id":"tt0108169","tmdb_id":"41128","title":"Snapdragon 1993","embed_url":"https:\/\/vidsrc.me\/embed\/movie?imdb=tt0108169","embed_url_tmdb":"https:\/\/vidsrc.me\/embed\/movie?tmdb=41128","quality":"1080p"},{"imdb_id":"tt0053879","tmdb_id":"63887","title":"The Great Impostor 1960","embed_url":"https:\/\/vidsrc.me\/embed\/movie?imdb=tt0053879","embed_url_tmdb":"https:\/\/vidsrc.me\/embed\/movie?tmdb=63887","quality":"1080p"},{"imdb_id":"tt0033916","tmdb_id":"106296","title":"The Monster and the Girl 1941","embed_url":"https:\/\/vidsrc.me\/embed\/movie?imdb=tt0033916","embed_url_tmdb":"https:\/\/vidsrc.me\/embed\/movie?tmdb=106296","quality":"1080p"},{"imdb_id":"tt1340107","tmdb_id":"44716","title":"In a Better World 2010","embed_url":"https:\/\/vidsrc.me\/embed\/movie?imdb=tt1340107","embed_url_tmdb":"https:\/\/vidsrc.me\/embed\/movie?tmdb=44716","quality":"1080p"},{"imdb_id":"tt0432006","tmdb_id":"201926","title":"Puppy 2005","embed_url":"https:\/\/vidsrc.me\/embed\/movie?imdb=tt0432006","embed_url_tmdb":"https:\/\/vidsrc.me\/embed\/movie?tmdb=201926","quality":"1080p"},{"imdb_id":"tt5566660","tmdb_id":"385390","title":"Love by Chance 2016","embed_url":"https:\/\/vidsrc.me\/embed\/movie?imdb=tt5566660","embed_url_tmdb":"https:\/\/vidsrc.me\/embed\/movie?tmdb=385390","quality":"1080p"},{"imdb_id":"tt0815244","tmdb_id":"10760","title":"Sydney White 2007","embed_url":"https:\/\/vidsrc.me\/embed\/movie?imdb=tt0815244","embed_url_tmdb":"https:\/\/vidsrc.me\/embed\/movie?tmdb=10760","quality":"1080p"},{"imdb_id":"tt0092834","tmdb_id":"28370","title":"Date with an Angel 1987","embed_url":"https:\/\/vidsrc.me\/embed\/movie?imdb=tt0092834","embed_url_tmdb":"https:\/\/vidsrc.me\/embed\/movie?tmdb=28370","quality":"1080p"},{"imdb_id":"tt0113114","tmdb_id":"9073","title":"Free Willy 2: The Adventure Home 1995","embed_url":"https:\/\/vidsrc.me\/embed\/movie?imdb=tt0113114","embed_url_tmdb":"https:\/\/vidsrc.me\/embed\/movie?tmdb=9073","quality":"1080p"},{"imdb_id":"tt1024733","tmdb_id":"4204","title":"$5 a Day 2008","embed_url":"https:\/\/vidsrc.me\/embed\/movie?imdb=tt1024733","embed_url_tmdb":"https:\/\/vidsrc.me\/embed\/movie?tmdb=4204","quality":"1080p"},{"imdb_id":"tt0401398","tmdb_id":"13417","title":"Kronk's New Groove 2005","embed_url":"https:\/\/vidsrc.me\/embed\/movie?imdb=tt0401398","embed_url_tmdb":"https:\/\/vidsrc.me\/embed\/movie?tmdb=13417","quality":"1080p"},{"imdb_id":"tt0384696","tmdb_id":"16394","title":"Winnie the Pooh: Springtime with Roo 2004","embed_url":"https:\/\/vidsrc.me\/embed\/movie?imdb=tt0384696","embed_url_tmdb":"https:\/\/vidsrc.me\/embed\/movie?tmdb=16394","quality":"1080p"},{"imdb_id":"tt0118604","tmdb_id":"9406","title":"An American Werewolf in Paris 1997","embed_url":"https:\/\/vidsrc.me\/embed\/movie?imdb=tt0118604","embed_url_tmdb":"https:\/\/vidsrc.me\/embed\/movie?tmdb=9406","quality":"1080p"},{"imdb_id":"tt0112691","tmdb_id":"532","title":"A Close Shave 1995","embed_url":"https:\/\/vidsrc.me\/embed\/movie?imdb=tt0112691","embed_url_tmdb":"https:\/\/vidsrc.me\/embed\/movie?tmdb=532","quality":"1080p"},{"imdb_id":"tt0108598","tmdb_id":"531","title":"The Wrong Trousers 1993","embed_url":"https:\/\/vidsrc.me\/embed\/movie?imdb=tt0108598","embed_url_tmdb":"https:\/\/vidsrc.me\/embed\/movie?tmdb=531","quality":"1080p"},{"imdb_id":"tt0104361","tmdb_id":"530","title":"A Grand Day Out 1989","embed_url":"https:\/\/vidsrc.me\/embed\/movie?imdb=tt0104361","embed_url_tmdb":"https:\/\/vidsrc.me\/embed\/movie?tmdb=530","quality":"1080p"},{"imdb_id":"tt0094715","tmdb_id":"15592","title":"Beaches 1988","embed_url":"https:\/\/vidsrc.me\/embed\/movie?imdb=tt0094715","embed_url_tmdb":"https:\/\/vidsrc.me\/embed\/movie?tmdb=15592","quality":"1080p"},{"imdb_id":"tt0033760","tmdb_id":"23014","title":"Invisible Ghost 1941","embed_url":"https:\/\/vidsrc.me\/embed\/movie?imdb=tt0033760","embed_url_tmdb":"https:\/\/vidsrc.me\/embed\/movie?tmdb=23014","quality":"1080p"},{"imdb_id":"tt0020960","tmdb_id":"22301","title":"Hell's Angels 1930","embed_url":"https:\/\/vidsrc.me\/embed\/movie?imdb=tt0020960","embed_url_tmdb":"https:\/\/vidsrc.me\/embed\/movie?tmdb=22301","quality":"1080p"},{"imdb_id":"tt0020697","tmdb_id":"228","title":"The Blue Angel 1930","embed_url":"https:\/\/vidsrc.me\/embed\/movie?imdb=tt0020697","embed_url_tmdb":"https:\/\/vidsrc.me\/embed\/movie?tmdb=228","quality":"1080p"},{"imdb_id":"tt2370228","tmdb_id":"340197","title":"All I Need 2016","embed_url":"https:\/\/vidsrc.me\/embed\/movie?imdb=tt2370228","embed_url_tmdb":"https:\/\/vidsrc.me\/embed\/movie?tmdb=340197","quality":"1080p"},{"imdb_id":"tt0173807","tmdb_id":"94738","title":"The Executioner Part II 1984","embed_url":"https:\/\/vidsrc.me\/embed\/movie?imdb=tt0173807","embed_url_tmdb":"https:\/\/vidsrc.me\/embed\/movie?tmdb=94738","quality":"1080p"},{"imdb_id":"tt0066454","tmdb_id":"277396","title":"Three Sisters 1970","embed_url":"https:\/\/vidsrc.me\/embed\/movie?imdb=tt0066454","embed_url_tmdb":"https:\/\/vidsrc.me\/embed\/movie?tmdb=277396","quality":"720p"},{"imdb_id":"tt10510654","tmdb_id":"573791","title":"The Battle: Roar to Victory 2019","embed_url":"https:\/\/vidsrc.me\/embed\/movie?imdb=tt10510654","embed_url_tmdb":"https:\/\/vidsrc.me\/embed\/movie?tmdb=573791","quality":"1080p"},{"imdb_id":"tt3644778","tmdb_id":"345466","title":"Istintobrass 2013","embed_url":"https:\/\/vidsrc.me\/embed\/movie?imdb=tt3644778","embed_url_tmdb":"https:\/\/vidsrc.me\/embed\/movie?tmdb=345466","quality":"1080p"},{"imdb_id":"tt0052289","tmdb_id":"47001","title":"The Thing That Couldn't Die 1958","embed_url":"https:\/\/vidsrc.me\/embed\/movie?imdb=tt0052289","embed_url_tmdb":"https:\/\/vidsrc.me\/embed\/movie?tmdb=47001","quality":"1080p"},{"imdb_id":"tt8649224","tmdb_id":"572632","title":"Aircraft Carrier Ibuki 2019","embed_url":"https:\/\/vidsrc.me\/embed\/movie?imdb=tt8649224","embed_url_tmdb":"https:\/\/vidsrc.me\/embed\/movie?tmdb=572632","quality":"1080p"},{"imdb_id":"tt0065604","tmdb_id":"69151","title":"The Cycle Savages 1969","embed_url":"https:\/\/vidsrc.me\/embed\/movie?imdb=tt0065604","embed_url_tmdb":"https:\/\/vidsrc.me\/embed\/movie?tmdb=69151","quality":"1080p"},{"imdb_id":"tt0063356","tmdb_id":"42633","title":"No Way to Treat a Lady 1968","embed_url":"https:\/\/vidsrc.me\/embed\/movie?imdb=tt0063356","embed_url_tmdb":"https:\/\/vidsrc.me\/embed\/movie?tmdb=42633","quality":"1080p"},{"imdb_id":"tt0021542","tmdb_id":"80705","title":"Westfront 1918 1930","embed_url":"https:\/\/vidsrc.me\/embed\/movie?imdb=tt0021542","embed_url_tmdb":"https:\/\/vidsrc.me\/embed\/movie?tmdb=80705","quality":"1080p"},{"imdb_id":"tt0077243","tmdb_id":"89922","title":"Blind Rage 1976","embed_url":"https:\/\/vidsrc.me\/embed\/movie?imdb=tt0077243","embed_url_tmdb":"https:\/\/vidsrc.me\/embed\/movie?tmdb=89922","quality":"1080p"},{"imdb_id":"tt0071968","tmdb_id":"58655","title":"Parade 1974","embed_url":"https:\/\/vidsrc.me\/embed\/movie?imdb=tt0071968","embed_url_tmdb":"https:\/\/vidsrc.me\/embed\/movie?tmdb=58655","quality":"1080p"},{"imdb_id":"tt5716438","tmdb_id":"434458","title":"Star Boys 2017","embed_url":"https:\/\/vidsrc.me\/embed\/movie?imdb=tt5716438","embed_url_tmdb":"https:\/\/vidsrc.me\/embed\/movie?tmdb=434458","quality":"1080p"},{"imdb_id":"tt3980372","tmdb_id":"461958","title":"Courageous Love 2017","embed_url":"https:\/\/vidsrc.me\/embed\/movie?imdb=tt3980372","embed_url_tmdb":"https:\/\/vidsrc.me\/embed\/movie?tmdb=461958","quality":"720p"},{"imdb_id":"tt3472894","tmdb_id":"289213","title":"Reel Rock 6 2011","embed_url":"https:\/\/vidsrc.me\/embed\/movie?imdb=tt3472894","embed_url_tmdb":"https:\/\/vidsrc.me\/embed\/movie?tmdb=289213","quality":"1080p"},{"imdb_id":"tt0037837","tmdb_id":"84711","title":"The Jungle Captive 1945","embed_url":"https:\/\/vidsrc.me\/embed\/movie?imdb=tt0037837","embed_url_tmdb":"https:\/\/vidsrc.me\/embed\/movie?tmdb=84711","quality":"1080p"},{"imdb_id":"tt0035713","tmdb_id":"84708","title":"Captive Wild Woman 1943","embed_url":"https:\/\/vidsrc.me\/embed\/movie?imdb=tt0035713","embed_url_tmdb":"https:\/\/vidsrc.me\/embed\/movie?tmdb=84708","quality":"1080p"}],"pages":1543}